cdo_api_client/Client.py
cdo_api_client/__init__.py
cdo_api_client/conf.py
cdo_api_client/exceptions.py
cdo_api_client/util.py
cdo_api_client-1.0.0.dev4.dist-info/DESCRIPTION.rst
cdo_api_client-1.0.0.dev4.dist-info/METADATA
cdo_api_client-1.0.0.dev4.dist-info/RECORD
cdo_api_client-1.0.0.dev4.dist-info/WHEEL
cdo_api_client-1.0.0.dev4.dist-info/metadata.json
cdo_api_client-1.0.0.dev4.dist-info/top_level.txt
